core_algorithms/__init__.py
core_algorithms/sorting/__init__.py
core_algorithms/sorting/bubble_sort.py
core_algorithms/sorting/insertion_sort.py
core_algorithms/sorting/merge_sort.py
core_algorithms/sorting/quick_sort.py
core_algorithms/sorting/selection_sort.py
core_algorithms-1.1.0.dist-info/LICENSE
core_algorithms-1.1.0.dist-info/METADATA
core_algorithms-1.1.0.dist-info/WHEEL
core_algorithms-1.1.0.dist-info/top_level.txt
core_algorithms-1.1.0.dist-info/RECORD
