Metadata-Version: 2.1
Name: core-algorithms
Version: 1.1.0
Summary: This project/library contains common algorithms...
Author-email: Alejandro Cora González <alek.cora.glez@gmail.com>
Maintainer: Alejandro Cora González
License: MIT
Project-URL: Homepage, https://gitlab.com/bytecode-solutions/core/core-algorithms
Project-URL: Repository, https://gitlab.com/bytecode-solutions/core/core-algorithms
Project-URL: Issues, https://gitlab.com/bytecode-solutions/core/core-algorithms/-/issues
Project-URL: Changelog, https://gitlab.com/bytecode-solutions/core/core-algorithms/-/blob/master/CHANGELOG.md
Classifier: License :: OSI Approved :: MIT License
Classifier: Intended Audience :: Developers
Classifier: Development Status :: 5 - Production/Stable
Classifier: Topic :: Software Development :: Libraries :: Python Modules
Classifier: Topic :: Utilities
Classifier: Programming Language :: Python :: 3
Classifier: Programming Language :: Python :: 3.7
Classifier: Programming Language :: Python :: 3.8
Classifier: Programming Language :: Python :: 3.9
Classifier: Programming Language :: Python :: 3.10
Classifier: Programming Language :: Python :: 3.11
Classifier: Programming Language :: Python :: 3.12
Classifier: Programming Language :: Python :: 3.13
Requires-Python: >=3.7
License-File: LICENSE
Requires-Dist: core-tests>=1.1.0
